easyad.py
easyad-1.0.9.dist-info/DESCRIPTION.rst
easyad-1.0.9.dist-info/METADATA
easyad-1.0.9.dist-info/RECORD
easyad-1.0.9.dist-info/WHEEL
easyad-1.0.9.dist-info/metadata.json
easyad-1.0.9.dist-info/top_level.txt
